pyfia/__init__.py
pyfia/py.typed
pyfia/validation.py
pyfia/constants/__init__.py
pyfia/constants/columns.py
pyfia/constants/defaults.py
pyfia/constants/plot_design.py
pyfia/constants/states.py
pyfia/constants/status_codes.py
pyfia/constants/tables.py
pyfia/core/__init__.py
pyfia/core/data_reader.py
pyfia/core/exceptions.py
pyfia/core/fia.py
pyfia/core/settings.py
pyfia/core/utils.py
pyfia/core/backends/__init__.py
pyfia/core/backends/base.py
pyfia/core/backends/duckdb_backend.py
pyfia/core/backends/motherduck_backend.py
pyfia/downloader/__init__.py
pyfia/downloader/cache.py
pyfia/downloader/client.py
pyfia/downloader/exceptions.py
pyfia/downloader/tables.py
pyfia/estimation/__init__.py
pyfia/estimation/aggregation.py
pyfia/estimation/base.py
pyfia/estimation/columns.py
pyfia/estimation/constants.py
pyfia/estimation/data_loading.py
pyfia/estimation/grm.py
pyfia/estimation/grm_base.py
pyfia/estimation/tree_expansion.py
pyfia/estimation/utils.py
pyfia/estimation/variance.py
pyfia/estimation/estimators/__init__.py
pyfia/estimation/estimators/area.py
pyfia/estimation/estimators/area_change.py
pyfia/estimation/estimators/biomass.py
pyfia/estimation/estimators/carbon.py
pyfia/estimation/estimators/carbon_flux.py
pyfia/estimation/estimators/carbon_pools.py
pyfia/estimation/estimators/growth.py
pyfia/estimation/estimators/mortality.py
pyfia/estimation/estimators/panel.py
pyfia/estimation/estimators/panel_validation.py
pyfia/estimation/estimators/removals.py
pyfia/estimation/estimators/tpa.py
pyfia/estimation/estimators/volume.py
pyfia/evalidator/__init__.py
pyfia/evalidator/client.py
pyfia/evalidator/estimate_types.py
pyfia/evalidator/validation.py
pyfia/filtering/__init__.py
pyfia/filtering/filters.py
pyfia/filtering/indicators.py
pyfia/filtering/parser.py
pyfia/filtering/utils.py
pyfia/utils/__init__.py
pyfia/utils/reference_tables.py
pyfia-1.2.0.dist-info/licenses/LICENSE
pyfia-1.2.0.dist-info/METADATA
pyfia-1.2.0.dist-info/WHEEL
pyfia-1.2.0.dist-info/top_level.txt
pyfia-1.2.0.dist-info/RECORD
