Metadata-Version: 2.4
Name: pyfia
Version: 1.2.0
Summary: High-performance Python library for Forest Inventory and Analysis (FIA) data analysis
Author-email: Chris Mihiar <28452317+mihiarc@users.noreply.github.com>
License: MIT
Project-URL: Homepage, https://fiatools.org/tools/pyfia/
Project-URL: Documentation, https://pyfia.fiatools.org/
Project-URL: Repository, https://github.com/mihiarc/pyfia
Project-URL: Issues, https://github.com/mihiarc/pyfia/issues
Project-URL: Changelog, https://github.com/mihiarc/pyfia/releases
Project-URL: Source Code, https://github.com/mihiarc/pyfia
Project-URL: FIA Ecosystem, https://fiatools.org
Keywords: fia,forest-inventory,usda,forestry,timber,duckdb,polars,analytics,big-data,biomass,carbon,volume,mortality,growth,statistics,estimation,variance,stratified-sampling,fiatools,evalidator,forest-analysis
Classifier: Development Status :: 4 - Beta
Classifier: Intended Audience :: Science/Research
Classifier: Intended Audience :: Developers
Classifier: Topic :: Scientific/Engineering :: GIS
Classifier: Topic :: Scientific/Engineering :: Bio-Informatics
Classifier: Topic :: Scientific/Engineering :: Information Analysis
Classifier: Topic :: Database
Classifier: License :: OSI Approved :: MIT License
Classifier: Operating System :: OS Independent
Classifier: Programming Language :: Python :: 3
Classifier: Programming Language :: Python :: 3.11
Classifier: Programming Language :: Python :: 3.12
Classifier: Programming Language :: Python :: 3.13
Classifier: Natural Language :: English
Classifier: Environment :: Console
Classifier: Framework :: Pydantic :: 2
Requires-Python: >=3.11
License-File: LICENSE
Requires-Dist: polars>=1.0.0
Requires-Dist: numpy>=1.26.0
Requires-Dist: connectorx>=0.3.1
Requires-Dist: duckdb>=0.9.0
Requires-Dist: pyarrow>=14.0.0
Requires-Dist: pydantic>=2.0.0
Requires-Dist: pydantic-settings>=2.0.0
Requires-Dist: rich
Requires-Dist: pyyaml>=6.0.0
Requires-Dist: pandas>=2.0.0
Requires-Dist: requests>=2.31.0
Provides-Extra: spatial
Requires-Dist: geopandas>=0.14.0; extra == "spatial"
Requires-Dist: shapely>=2.0.0; extra == "spatial"
Provides-Extra: pandas
Requires-Dist: pandas>=2.0.0; extra == "pandas"
Provides-Extra: dev
Requires-Dist: pytest>=8.4.1; extra == "dev"
Requires-Dist: pytest-cov>=6.2.1; extra == "dev"
Requires-Dist: ruff>=0.12.0; extra == "dev"
Requires-Dist: mypy>=1.16.1; extra == "dev"
Requires-Dist: types-requests>=2.32.0; extra == "dev"
Requires-Dist: hypothesis>=6.130.0; extra == "dev"
Requires-Dist: hypothesis[numpy]>=6.130.0; extra == "dev"
Requires-Dist: mkdocs>=1.6.0; extra == "dev"
Requires-Dist: mkdocs-material>=9.5.0; extra == "dev"
Requires-Dist: pre-commit>=3.6.0; extra == "dev"
Provides-Extra: all
Requires-Dist: pyfia[dev,pandas,spatial]; extra == "all"
Dynamic: license-file
